duckduckgo_mcp_server/__init__.py
duckduckgo_mcp_server/server.py
duckduckgo_mcp_server_maintained-0.1.3.dist-info/METADATA
duckduckgo_mcp_server_maintained-0.1.3.dist-info/WHEEL
duckduckgo_mcp_server_maintained-0.1.3.dist-info/entry_points.txt
duckduckgo_mcp_server_maintained-0.1.3.dist-info/licenses/LICENSE
duckduckgo_mcp_server_maintained-0.1.3.dist-info/RECORD
