Metadata-Version: 2.4
Name: duckduckgo-mcp-server-maintained
Version: 0.1.3
Summary: MCP Server for searching via DuckDuckGo (Maintained Fork)
Project-URL: Homepage, https://github.com/scalabrese/duckduckgo-mcp-server
Project-URL: Issues, https://github.com/scalabrese/duckduckgo-mcp-server/issues
Project-URL: Original Project, https://github.com/nickclyde/duckduckgo-mcp-server
Author-email: Nick Clyde <nick@clyde.tech>, Your Name <your.email@example.com>
License-File: LICENSE
Classifier: Development Status :: 3 - Alpha
Classifier: Intended Audience :: Developers
Classifier: License :: OSI Approved :: MIT License
Classifier: Programming Language :: Python :: 3
Classifier: Programming Language :: Python :: 3.10
Classifier: Programming Language :: Python :: 3.11
Classifier: Programming Language :: Python :: 3.12
Classifier: Programming Language :: Python :: 3.13
Requires-Python: >=3.10
Requires-Dist: beautifulsoup4>=4.13.3
Requires-Dist: httpx>=0.28.1
Requires-Dist: mcp[cli]>=1.3.0
